self_reasoning_tokens_pytorch/__init__.py
self_reasoning_tokens_pytorch/attention_with_stop_graddable_qkv.py
self_reasoning_tokens_pytorch/self_reasoning_tokens.py
self_reasoning_tokens_pytorch-0.0.4.dist-info/LICENSE
self_reasoning_tokens_pytorch-0.0.4.dist-info/METADATA
self_reasoning_tokens_pytorch-0.0.4.dist-info/WHEEL
self_reasoning_tokens_pytorch-0.0.4.dist-info/top_level.txt
self_reasoning_tokens_pytorch-0.0.4.dist-info/RECORD
