Metadata-Version: 2.1
Name: self-reasoning-tokens-pytorch
Version: 0.0.4
Summary: Self Reasoning Tokens
Home-page: https://github.com/lucidrains/self-reasoning-tokens-pytorch
Author: Phil Wang
Author-email: lucidrains@gmail.com
License: MIT
Keywords: artificial intelligence,deep learning,transformers,attention mechanism,adaptive computation
Classifier: Development Status :: 4 - Beta
Classifier: Intended Audience :: Developers
Classifier: Topic :: Scientific/Engineering :: Artificial Intelligence
Classifier: License :: OSI Approved :: MIT License
Classifier: Programming Language :: Python :: 3.7
License-File: LICENSE
Requires-Dist: einops >=0.8.0
Requires-Dist: x-transformers >=1.28.4
Requires-Dist: torch >=2.0
